[
    {
        "wrapperType": "track",
        "kind": "song",
        "artistId": 274199627,
        "collectionId": 355862514,
        "trackId": 355862516,
        "artistName": "Fool's Gold",
        "collectionName": "Fool's Gold (Bonus Edition)",
        "trackName": "Surprise Hotel",
        "collectionCensoredName": "Fool's Gold (Bonus Edition)",
        "trackCensoredName": "Surprise Hotel",
        "artistViewUrl": "https://itunes.apple.com/fr/artist/fools-gold/id274199627?uo=4",
        "collectionViewUrl": "https://itunes.apple.com/fr/album/surprise-hotel/id355862514?i=355862516&uo=4",
        "trackViewUrl": "https://itunes.apple.com/fr/album/surprise-hotel/id355862514?i=355862516&uo=4",
        "previewUrl": "http://a631.phobos.apple.com/us/r1000/074/Music/v4/13/53/2d/13532d5a-42d0-599e-6a13-61f4d72b11fb/mzaf_1246009595928277036.aac.m4a",
        "artworkUrl30": "http://is2.mzstatic.com/image/pf/us/r30/Music/e1/5f/37/mzi.rncwhpqs.30x30-50.jpg",
        "artworkUrl60": "http://is1.mzstatic.com/image/pf/us/r30/Music/e1/5f/37/mzi.rncwhpqs.60x60-50.jpg",
        "artworkUrl100": "http://is3.mzstatic.com/image/pf/us/r30/Music/e1/5f/37/mzi.rncwhpqs.100x100-75.jpg",
        "collectionPrice": 9.99,
        "trackPrice": 1.29,
        "releaseDate": "2010-03-01T08:00:00Z",
        "collectionExplicitness": "notExplicit",
        "trackExplicitness": "notExplicit",
        "discCount": 1,
        "discNumber": 1,
        "trackCount": 12,
        "trackNumber": 1,
        "trackTimeMillis": 407884,
        "country": "FRA",
        "currency": "EUR",
        "primaryGenreName": "Alternative",
        "isStreamable": true
    },
    {
        "wrapperType": "track",
        "kind": "song",
        "artistId": 274199627,
        "collectionId": 355862514,
        "trackId": 355862606,
        "artistName": "Fool's Gold",
        "collectionName": "Fool's Gold (Bonus Edition)",
        "trackName": "Surprise Hotel (Micachu & The Shapes Remix)",
        "collectionCensoredName": "Fool's Gold (Bonus Edition)",
        "trackCensoredName": "Surprise Hotel (Micachu & The Shapes Remix)",
        "artistViewUrl": "https://itunes.apple.com/fr/artist/fools-gold/id274199627?uo=4",
        "collectionViewUrl": "https://itunes.apple.com/fr/album/surprise-hotel-micachu-shapes/id355862514?i=355862606&uo=4",
        "trackViewUrl": "https://itunes.apple.com/fr/album/surprise-hotel-micachu-shapes/id355862514?i=355862606&uo=4",
        "previewUrl": "http://a89.phobos.apple.com/us/r1000/064/Music/v4/4f/08/93/4f089361-69d0-c08b-38b2-211f4e8a92e8/mzaf_8269119765356451061.aac.m4a",
        "artworkUrl30": "http://is2.mzstatic.com/image/pf/us/r30/Music/e1/5f/37/mzi.rncwhpqs.30x30-50.jpg",
        "artworkUrl60": "http://is1.mzstatic.com/image/pf/us/r30/Music/e1/5f/37/mzi.rncwhpqs.60x60-50.jpg",
        "artworkUrl100": "http://is3.mzstatic.com/image/pf/us/r30/Music/e1/5f/37/mzi.rncwhpqs.100x100-75.jpg",
        "collectionPrice": 9.99,
        "trackPrice": 1.29,
        "releaseDate": "2010-03-01T08:00:00Z",
        "collectionExplicitness": "notExplicit",
        "trackExplicitness": "notExplicit",
        "discCount": 1,
        "discNumber": 1,
        "trackCount": 12,
        "trackNumber": 12,
        "trackTimeMillis": 210763,
        "country": "FRA",
        "currency": "EUR",
        "primaryGenreName": "Alternative",
        "isStreamable": true
    },
    {
        "wrapperType": "track",
        "kind": "song",
        "artistId": 274199627,
        "collectionId": 355862514,
        "trackId": 355862572,
        "artistName": "Fool's Gold",
        "collectionName": "Fool's Gold (Bonus Edition)",
        "trackName": "Surprise Hotel (Mad Decent Toadz Remix)",
        "collectionCensoredName": "Fool's Gold (Bonus Edition)",
        "trackCensoredName": "Surprise Hotel (Mad Decent Toadz Remix)",
        "artistViewUrl": "https://itunes.apple.com/fr/artist/fools-gold/id274199627?uo=4",
        "collectionViewUrl": "https://itunes.apple.com/fr/album/surprise-hotel-mad-decent/id355862514?i=355862572&uo=4",
        "trackViewUrl": "https://itunes.apple.com/fr/album/surprise-hotel-mad-decent/id355862514?i=355862572&uo=4",
        "previewUrl": "http://a444.phobos.apple.com/us/r1000/099/Music/v4/68/a1/2c/68a12cc6-52ca-1603-351e-becb41ababaa/mzaf_8650799448065949684.aac.m4a",
        "artworkUrl30": "http://is2.mzstatic.com/image/pf/us/r30/Music/e1/5f/37/mzi.rncwhpqs.30x30-50.jpg",
        "artworkUrl60": "http://is1.mzstatic.com/image/pf/us/r30/Music/e1/5f/37/mzi.rncwhpqs.60x60-50.jpg",
        "artworkUrl100": "http://is3.mzstatic.com/image/pf/us/r30/Music/e1/5f/37/mzi.rncwhpqs.100x100-75.jpg",
        "collectionPrice": 9.99,
        "trackPrice": 1.29,
        "releaseDate": "2010-03-01T08:00:00Z",
        "collectionExplicitness": "notExplicit",
        "trackExplicitness": "notExplicit",
        "discCount": 1,
        "discNumber": 1,
        "trackCount": 12,
        "trackNumber": 9,
        "trackTimeMillis": 238042,
        "country": "FRA",
        "currency": "EUR",
        "primaryGenreName": "Alternative",
        "isStreamable": true
    }
]